[{"date":"2025-02-07","open":105.0,"high":116.56,"low":105.0,"close":105.0,"volume":10480710},{"date":"2025-02-10","open":106.4,"high":116.7,"low":104.32,"close":110.6,"volume":5814893},{"date":"2025-02-11","open":112.3,"high":121.7,"low":111.0,"close":115.4,"volume":3388671},{"date":"2025-02-12","open":116.0,"high":118.0,"low":106.6,"close":108.0,"volume":4307957},{"date":"2025-02-13","open":105.3,"high":107.3,"low":103.0,"close":105.3,"volume":2104376},{"date":"2025-02-14","open":107.0,"high":113.4,"low":106.9,"close":111.0,"volume":1400525},{"date":"2025-02-17","open":109.5,"high":110.0,"low":106.1,"close":106.8,"volume":726294},{"date":"2025-02-18","open":109.9,"high":110.0,"low":106.6,"close":107.4,"volume":739570},{"date":"2025-02-19","open":107.2,"high":109.0,"low":106.0,"close":106.6,"volume":713801},{"date":"2025-02-20","open":106.6,"high":109.0,"low":105.3,"close":105.3,"volume":581335},{"date":"2025-02-21","open":105.7,"high":110.5,"low":105.7,"close":110.0,"volume":1478957},{"date":"2025-02-24","open":108.0,"high":109.1,"low":106.6,"close":107.6,"volume":451428},{"date":"2025-02-25","open":107.4,"high":107.5,"low":104.2,"close":104.2,"volume":557463},{"date":"2025-02-26","open":104.0,"high":106.0,"low":102.5,"close":102.5,"volume":511354},{"date":"2025-02-27","open":102.0,"high":102.9,"low":100.0,"close":100.1,"volume":729325},{"date":"2025-02-28","open":100.0,"high":101.2,"low":98.8,"close":99.45,"volume":865675},{"date":"2025-03-03","open":98.25,"high":99.95,"low":95.8,"close":97.5,"volume":1076255},{"date":"2025-03-04","open":96.6,"high":97.2,"low":93.65,"close":93.95,"volume":1231365},{"date":"2025-03-05","open":94.6,"high":97.6,"low":94.6,"close":96.3,"volume":910813},{"date":"2025-03-06","open":97.1,"high":98.8,"low":94.05,"close":94.05,"volume":538658},{"date":"2025-03-07","open":93.5,"high":94.3,"low":92.05,"close":94.1,"volume":487810},{"date":"2025-03-10","open":93.8,"high":96.55,"low":91.05,"close":91.05,"volume":582080},{"date":"2025-03-11","open":91.0,"high":91.45,"low":88.15,"close":88.6,"volume":902736},{"date":"2025-03-12","open":90.0,"high":94.35,"low":89.6,"close":93.7,"volume":1408421},{"date":"2025-03-13","open":93.0,"high":95.85,"low":92.2,"close":95.0,"volume":571439},{"date":"2025-03-14","open":94.8,"high":98.85,"low":94.75,"close":95.7,"volume":652597},{"date":"2025-03-17","open":94.6,"high":95.75,"low":93.2,"close":94.15,"volume":404774},{"date":"2025-03-18","open":94.1,"high":95.05,"low":93.45,"close":94.6,"volume":562327},{"date":"2025-03-19","open":94.6,"high":95.35,"low":94.15,"close":94.65,"volume":324852},{"date":"2025-03-20","open":94.7,"high":97.65,"low":94.35,"close":97.5,"volume":268083},{"date":"2025-03-21","open":97.05,"high":97.05,"low":93.45,"close":95.3,"volume":1234124},{"date":"2025-03-24","open":95.3,"high":96.98,"low":94.65,"close":95.15,"volume":490416},{"date":"2025-03-25","open":95.11,"high":95.11,"low":93.3,"close":94.71,"volume":329702},{"date":"2025-03-26","open":94.82,"high":95.24,"low":93.76,"close":94.68,"volume":404210},{"date":"2025-03-27","open":94.0,"high":95.0,"low":92.3,"close":92.96,"volume":464356},{"date":"2025-03-28","open":92.02,"high":92.21,"low":89.95,"close":92.14,"volume":425076},{"date":"2025-03-31","open":91.21,"high":91.7,"low":90.0,"close":91.5,"volume":346610},{"date":"2025-04-01","open":91.3,"high":93.27,"low":91.0,"close":92.78,"volume":383897},{"date":"2025-04-02","open":92.78,"high":97.48,"low":92.5,"close":97.19,"volume":551996},{"date":"2025-04-03","open":95.63,"high":97.0,"low":92.87,"close":95.0,"volume":407811},{"date":"2025-04-04","open":94.0,"high":95.2,"low":89.4,"close":90.5,"volume":744904},{"date":"2025-04-07","open":83.8,"high":88.62,"low":83.3,"close":85.4,"volume":825802},{"date":"2025-04-08","open":88.0,"high":90.26,"low":86.53,"close":88.8,"volume":349820},{"date":"2025-04-09","open":85.76,"high":86.68,"low":83.31,"close":85.09,"volume":511637},{"date":"2025-04-10","open":92.0,"high":92.38,"low":89.1,"close":91.26,"volume":433273},{"date":"2025-04-11","open":90.86,"high":91.94,"low":88.71,"close":89.99,"volume":215961},{"date":"2025-04-14","open":91.2,"high":92.78,"low":90.19,"close":90.79,"volume":324803},{"date":"2025-04-15","open":90.8,"high":92.78,"low":90.75,"close":92.7,"volume":388193},{"date":"2025-04-16","open":92.68,"high":92.68,"low":90.3,"close":92.2,"volume":430346},{"date":"2025-04-17","open":92.2,"high":92.5,"low":90.82,"close":91.0,"volume":89273},{"date":"2025-04-22","open":91.0,"high":94.14,"low":89.5,"close":94.14,"volume":151936},{"date":"2025-04-23","open":95.0,"high":96.7,"low":94.4,"close":96.0,"volume":219245},{"date":"2025-04-24","open":95.77,"high":97.35,"low":94.29,"close":96.7,"volume":214515},{"date":"2025-04-25","open":96.75,"high":102.78,"low":96.75,"close":100.56,"volume":411375},{"date":"2025-04-28","open":100.5,"high":103.86,"low":99.56,"close":103.16,"volume":873907},{"date":"2025-04-29","open":103.4,"high":105.8,"low":102.36,"close":105.72,"volume":220822},{"date":"2025-04-30","open":106.0,"high":106.84,"low":103.7,"close":106.5,"volume":184019},{"date":"2025-05-02","open":106.5,"high":109.0,"low":105.92,"close":108.0,"volume":327534},{"date":"2025-05-05","open":107.34,"high":109.1,"low":107.0,"close":108.2,"volume":767691},{"date":"2025-05-06","open":108.52,"high":110.2,"low":107.1,"close":110.02,"volume":476277},{"date":"2025-05-07","open":110.0,"high":112.56,"low":107.88,"close":107.88,"volume":405836},{"date":"2025-05-08","open":107.0,"high":112.5,"low":106.5,"close":112.0,"volume":350171},{"date":"2025-05-09","open":111.4,"high":113.52,"low":111.4,"close":113.0,"volume":453144},{"date":"2025-05-12","open":113.0,"high":117.4,"low":113.0,"close":117.4,"volume":485880},{"date":"2025-05-13","open":116.4,"high":119.76,"low":115.22,"close":119.5,"volume":349055},{"date":"2025-05-14","open":119.5,"high":120.58,"low":118.28,"close":118.52,"volume":689441},{"date":"2025-05-15","open":118.38,"high":119.4,"low":117.44,"close":118.14,"volume":145488},{"date":"2025-05-16","open":118.14,"high":118.98,"low":114.9,"close":116.7,"volume":204455},{"date":"2025-05-19","open":116.24,"high":118.1,"low":114.9,"close":118.1,"volume":283804},{"date":"2025-05-20","open":118.0,"high":118.42,"low":115.86,"close":117.82,"volume":389367},{"date":"2025-05-21","open":127.66,"high":128.56,"low":120.08,"close":126.44,"volume":2917625},{"date":"2025-05-22","open":124.84,"high":125.84,"low":120.72,"close":122.76,"volume":667915},{"date":"2025-05-23","open":122.72,"high":124.44,"low":116.66,"close":122.94,"volume":599947},{"date":"2025-05-26","open":124.8,"high":127.82,"low":123.98,"close":127.82,"volume":644435},{"date":"2025-05-27","open":127.42,"high":131.62,"low":126.16,"close":129.36,"volume":551098},{"date":"2025-05-28","open":129.36,"high":131.1,"low":128.02,"close":129.8,"volume":854628},{"date":"2025-05-30","open":129.0,"high":129.88,"low":126.44,"close":129.88,"volume":1017069},{"date":"2025-06-02","open":129.4,"high":131.5,"low":128.38,"close":130.18,"volume":452540},{"date":"2025-06-03","open":130.18,"high":130.98,"low":127.22,"close":128.34,"volume":241760},{"date":"2025-06-04","open":128.76,"high":131.04,"low":128.76,"close":131.04,"volume":532344},{"date":"2025-06-05","open":131.0,"high":131.66,"low":128.0,"close":128.82,"volume":309755},{"date":"2025-06-09","open":128.06,"high":129.88,"low":127.74,"close":128.78,"volume":349948},{"date":"2025-06-10","open":128.58,"high":133.58,"low":127.76,"close":133.48,"volume":791123},{"date":"2025-06-11","open":133.2,"high":133.2,"low":129.2,"close":130.3,"volume":633002},{"date":"2025-06-12","open":130.0,"high":130.8,"low":128.38,"close":130.0,"volume":707489},{"date":"2025-06-13","open":127.6,"high":128.3,"low":124.84,"close":127.58,"volume":621666},{"date":"2025-06-16","open":127.2,"high":127.9,"low":124.12,"close":125.0,"volume":474876},{"date":"2025-06-17","open":124.7,"high":125.4,"low":122.52,"close":124.96,"volume":336512},{"date":"2025-06-18","open":124.68,"high":125.32,"low":123.5,"close":125.12,"volume":296425},{"date":"2025-06-19","open":125.0,"high":125.0,"low":121.86,"close":121.86,"volume":979814},{"date":"2025-06-23","open":120.86,"high":124.04,"low":120.06,"close":123.74,"volume":236502},{"date":"2025-06-24","open":125.0,"high":125.68,"low":122.42,"close":124.12,"volume":227578},{"date":"2025-06-25","open":124.12,"high":125.1,"low":122.78,"close":123.26,"volume":235625},{"date":"2025-06-26","open":122.88,"high":125.02,"low":122.5,"close":124.5,"volume":351134},{"date":"2025-06-27","open":124.84,"high":125.48,"low":123.84,"close":125.0,"volume":201423},{"date":"2025-06-30","open":125.0,"high":126.62,"low":123.8,"close":125.0,"volume":238068},{"date":"2025-07-01","open":125.0,"high":125.18,"low":124.22,"close":124.56,"volume":109779},{"date":"2025-07-02","open":124.58,"high":125.0,"low":122.22,"close":124.8,"volume":186941},{"date":"2025-07-03","open":123.9,"high":125.06,"low":123.04,"close":124.94,"volume":129016},{"date":"2025-07-04","open":124.6,"high":125.0,"low":122.64,"close":124.14,"volume":103185},{"date":"2025-07-07","open":123.94,"high":126.78,"low":123.04,"close":125.24,"volume":191807},{"date":"2025-07-08","open":124.9,"high":125.18,"low":121.04,"close":122.6,"volume":208700},{"date":"2025-07-09","open":122.42,"high":123.68,"low":121.1,"close":121.1,"volume":186777},{"date":"2025-07-10","open":121.04,"high":125.1,"low":120.94,"close":124.94,"volume":177886},{"date":"2025-07-11","open":124.94,"high":125.96,"low":123.34,"close":123.82,"volume":106151},{"date":"2025-07-14","open":123.24,"high":124.5,"low":122.8,"close":124.0,"volume":107428},{"date":"2025-07-15","open":123.8,"high":125.58,"low":123.14,"close":124.2,"volume":221592},{"date":"2025-07-16","open":123.96,"high":125.56,"low":123.02,"close":124.68,"volume":129814},{"date":"2025-07-17","open":124.82,"high":126.1,"low":124.14,"close":125.88,"volume":195153},{"date":"2025-07-18","open":125.96,"high":127.92,"low":125.58,"close":127.48,"volume":229934},{"date":"2025-07-21","open":127.54,"high":127.64,"low":123.3,"close":125.08,"volume":227117},{"date":"2025-07-22","open":124.0,"high":124.98,"low":123.2,"close":123.62,"volume":129355},{"date":"2025-07-23","open":123.22,"high":124.76,"low":123.22,"close":124.18,"volume":208400},{"date":"2025-07-24","open":124.0,"high":125.94,"low":121.48,"close":122.36,"volume":183268},{"date":"2025-07-25","open":122.1,"high":124.34,"low":121.14,"close":124.0,"volume":164868},{"date":"2025-07-28","open":123.86,"high":126.94,"low":123.34,"close":124.24,"volume":156053},{"date":"2025-07-29","open":124.0,"high":125.0,"low":123.08,"close":123.92,"volume":127809},{"date":"2025-07-30","open":123.0,"high":124.54,"low":121.74,"close":124.04,"volume":176839},{"date":"2025-07-31","open":124.0,"high":125.18,"low":123.36,"close":123.64,"volume":344050},{"date":"2025-08-01","open":122.0,"high":124.74,"low":122.0,"close":124.34,"volume":165872},{"date":"2025-08-04","open":124.34,"high":127.48,"low":123.58,"close":127.24,"volume":289005},{"date":"2025-08-05","open":128.22,"high":130.16,"low":126.76,"close":127.82,"volume":277414},{"date":"2025-08-06","open":128.0,"high":128.88,"low":124.36,"close":125.0,"volume":189914},{"date":"2025-08-07","open":124.0,"high":125.52,"low":123.3,"close":124.0,"volume":198067},{"date":"2025-08-08","open":129.1,"high":131.5,"low":122.92,"close":124.64,"volume":1339887},{"date":"2025-08-11","open":127.28,"high":127.54,"low":123.8,"close":125.16,"volume":1864573},{"date":"2025-08-12","open":125.2,"high":125.68,"low":121.78,"close":122.06,"volume":259342},{"date":"2025-08-13","open":117.9,"high":120.0,"low":117.16,"close":118.12,"volume":5727529},{"date":"2025-08-14","open":117.34,"high":120.92,"low":117.12,"close":120.5,"volume":389605},{"date":"2025-08-15","open":120.98,"high":121.4,"low":116.84,"close":116.86,"volume":206847},{"date":"2025-08-18","open":117.08,"high":117.46,"low":116.2,"close":117.32,"volume":194842},{"date":"2025-08-19","open":117.38,"high":118.54,"low":117.02,"close":117.3,"volume":253821},{"date":"2025-08-20","open":117.1,"high":117.4,"low":116.08,"close":116.96,"volume":145686},{"date":"2025-08-21","open":116.78,"high":117.18,"low":115.8,"close":116.5,"volume":155528},{"date":"2025-08-22","open":116.5,"high":117.5,"low":116.5,"close":116.66,"volume":234813},{"date":"2025-08-25","open":116.78,"high":117.16,"low":115.96,"close":116.62,"volume":506017},{"date":"2025-08-26","open":116.42,"high":116.58,"low":113.74,"close":113.74,"volume":1175218},{"date":"2025-08-27","open":113.96,"high":118.0,"low":113.96,"close":117.9,"volume":281360},{"date":"2025-08-28","open":117.96,"high":118.56,"low":114.16,"close":114.16,"volume":144153},{"date":"2025-08-29","open":114.6,"high":115.14,"low":114.0,"close":114.54,"volume":248974},{"date":"2025-09-01","open":114.5,"high":115.2,"low":113.22,"close":113.98,"volume":144403},{"date":"2025-09-02","open":114.0,"high":114.44,"low":110.24,"close":111.76,"volume":250825},{"date":"2025-09-03","open":112.06,"high":114.4,"low":111.96,"close":112.28,"volume":413668},{"date":"2025-09-04","open":112.7,"high":116.2,"low":112.7,"close":116.08,"volume":202746},{"date":"2025-09-05","open":116.64,"high":119.0,"low":116.64,"close":117.84,"volume":213614},{"date":"2025-09-08","open":117.96,"high":119.48,"low":117.1,"close":119.32,"volume":143150},{"date":"2025-09-09","open":118.9,"high":119.5,"low":115.9,"close":116.86,"volume":457532},{"date":"2025-09-10","open":116.9,"high":118.08,"low":116.66,"close":117.48,"volume":187348},{"date":"2025-09-11","open":117.78,"high":118.48,"low":116.7,"close":117.42,"volume":101918},{"date":"2025-09-12","open":116.88,"high":118.16,"low":116.3,"close":117.0,"volume":90468},{"date":"2025-09-15","open":117.0,"high":120.08,"low":116.98,"close":118.64,"volume":842115},{"date":"2025-09-16","open":118.64,"high":121.22,"low":118.64,"close":118.78,"volume":264671},{"date":"2025-09-17","open":118.7,"high":119.0,"low":116.5,"close":117.32,"volume":132243},{"date":"2025-09-18","open":117.34,"high":119.6,"low":117.3,"close":119.6,"volume":163724},{"date":"2025-09-19","open":119.5,"high":120.2,"low":118.16,"close":120.0,"volume":321673},{"date":"2025-09-22","open":120.0,"high":120.54,"low":119.28,"close":120.48,"volume":355529},{"date":"2025-09-23","open":120.2,"high":122.68,"low":120.2,"close":121.9,"volume":218272},{"date":"2025-09-24","open":121.5,"high":121.5,"low":119.86,"close":119.86,"volume":196364},{"date":"2025-09-25","open":119.2,"high":119.96,"low":118.42,"close":118.68,"volume":192407},{"date":"2025-09-26","open":118.96,"high":119.28,"low":116.38,"close":116.62,"volume":122543},{"date":"2025-09-29","open":117.88,"high":120.58,"low":116.76,"close":119.7,"volume":218152},{"date":"2025-09-30","open":119.28,"high":121.16,"low":118.7,"close":120.5,"volume":642867},{"date":"2025-10-01","open":121.0,"high":122.0,"low":119.68,"close":121.4,"volume":143088},{"date":"2025-10-02","open":121.38,"high":123.46,"low":121.38,"close":122.32,"volume":154951},{"date":"2025-10-03","open":120.0,"high":123.5,"low":119.94,"close":122.46,"volume":343623},{"date":"2025-10-06","open":122.2,"high":125.1,"low":121.5,"close":123.76,"volume":459086},{"date":"2025-10-07","open":123.92,"high":124.82,"low":122.44,"close":123.08,"volume":247614},{"date":"2025-10-08","open":124.52,"high":125.0,"low":123.06,"close":123.74,"volume":215439},{"date":"2025-10-09","open":123.5,"high":123.86,"low":121.28,"close":122.04,"volume":212816},{"date":"2025-10-10","open":122.04,"high":123.0,"low":119.36,"close":119.36,"volume":209111},{"date":"2025-10-13","open":119.36,"high":120.46,"low":118.12,"close":118.34,"volume":89953},{"date":"2025-10-14","open":117.42,"high":118.32,"low":117.0,"close":118.0,"volume":463686},{"date":"2025-10-15","open":118.6,"high":119.5,"low":117.78,"close":118.56,"volume":238262},{"date":"2025-10-16","open":118.0,"high":118.56,"low":117.0,"close":117.86,"volume":202370},{"date":"2025-10-17","open":117.72,"high":117.72,"low":113.78,"close":115.8,"volume":286422},{"date":"2025-10-20","open":115.68,"high":117.86,"low":115.68,"close":117.52,"volume":142443},{"date":"2025-10-21","open":117.52,"high":119.74,"low":116.34,"close":119.38,"volume":155541},{"date":"2025-10-22","open":119.9,"high":121.0,"low":118.32,"close":120.36,"volume":171189},{"date":"2025-10-23","open":120.28,"high":121.12,"low":117.86,"close":121.04,"volume":316954},{"date":"2025-10-24","open":121.04,"high":124.34,"low":120.82,"close":123.92,"volume":177483},{"date":"2025-10-27","open":123.7,"high":124.0,"low":122.02,"close":122.44,"volume":118744},{"date":"2025-10-28","open":122.44,"high":122.44,"low":121.3,"close":121.96,"volume":89671},{"date":"2025-10-29","open":121.78,"high":123.24,"low":120.92,"close":123.06,"volume":125082},{"date":"2025-10-30","open":122.7,"high":123.56,"low":122.04,"close":123.56,"volume":131346},{"date":"2025-10-31","open":123.56,"high":123.92,"low":122.24,"close":122.68,"volume":151704},{"date":"2025-11-03","open":122.68,"high":124.1,"low":121.78,"close":123.18,"volume":147817},{"date":"2025-11-04","open":123.38,"high":124.06,"low":121.74,"close":123.5,"volume":260488},{"date":"2025-11-05","open":123.04,"high":123.72,"low":121.48,"close":123.72,"volume":182794},{"date":"2025-11-06","open":123.0,"high":123.36,"low":118.26,"close":118.34,"volume":344313},{"date":"2025-11-07","open":118.12,"high":119.0,"low":114.5,"close":117.3,"volume":214079},{"date":"2025-11-10","open":117.02,"high":118.68,"low":116.78,"close":117.9,"volume":106901},{"date":"2025-11-11","open":117.44,"high":118.28,"low":115.74,"close":118.1,"volume":149206},{"date":"2025-11-12","open":116.82,"high":121.26,"low":116.82,"close":120.74,"volume":261539},{"date":"2025-11-13","open":120.74,"high":122.0,"low":119.18,"close":119.18,"volume":105371},{"date":"2025-11-14","open":119.0,"high":119.0,"low":116.7,"close":117.7,"volume":162207},{"date":"2025-11-17","open":118.26,"high":120.0,"low":117.34,"close":117.34,"volume":208890},{"date":"2025-11-18","open":116.58,"high":117.0,"low":115.28,"close":115.96,"volume":259322},{"date":"2025-11-19","open":115.9,"high":117.32,"low":115.04,"close":116.3,"volume":281738},{"date":"2025-11-20","open":123.92,"high":124.0,"low":111.66,"close":111.66,"volume":1184710},{"date":"2025-11-21","open":110.6,"high":113.26,"low":109.7,"close":111.04,"volume":413980},{"date":"2025-11-24","open":111.1,"high":112.28,"low":110.7,"close":111.6,"volume":398412},{"date":"2025-11-25","open":112.06,"high":113.3,"low":111.54,"close":112.38,"volume":203007},{"date":"2025-11-26","open":112.72,"high":114.38,"low":112.38,"close":114.22,"volume":206407},{"date":"2025-11-27","open":114.2,"high":116.34,"low":113.94,"close":116.32,"volume":210793},{"date":"2025-11-28","open":116.64,"high":117.12,"low":115.42,"close":116.4,"volume":566906},{"date":"2025-12-01","open":116.62,"high":116.62,"low":113.78,"close":115.2,"volume":766487},{"date":"2025-12-02","open":115.2,"high":115.34,"low":113.94,"close":114.0,"volume":154604},{"date":"2025-12-03","open":114.46,"high":114.8,"low":110.06,"close":110.66,"volume":287981},{"date":"2025-12-04","open":111.0,"high":112.46,"low":110.2,"close":112.24,"volume":260133},{"date":"2025-12-05","open":112.0,"high":114.5,"low":111.8,"close":112.52,"volume":124579},{"date":"2025-12-08","open":112.5,"high":112.5,"low":110.6,"close":110.62,"volume":216378},{"date":"2025-12-09","open":110.6,"high":110.6,"low":108.02,"close":108.02,"volume":265670},{"date":"2025-12-10","open":108.12,"high":109.42,"low":107.4,"close":109.28,"volume":297735},{"date":"2025-12-11","open":109.5,"high":109.5,"low":105.6,"close":106.62,"volume":649418},{"date":"2025-12-12","open":107.8,"high":108.8,"low":106.4,"close":106.78,"volume":389693},{"date":"2025-12-15","open":106.78,"high":107.36,"low":105.44,"close":105.78,"volume":320924},{"date":"2025-12-16","open":105.7,"high":105.98,"low":104.18,"close":105.06,"volume":207414},{"date":"2025-12-17","open":106.18,"high":106.4,"low":103.42,"close":103.82,"volume":188149},{"date":"2025-12-18","open":103.5,"high":104.7,"low":102.72,"close":104.58,"volume":197523},{"date":"2025-12-19","open":104.58,"high":105.1,"low":103.88,"close":104.26,"volume":498176},{"date":"2025-12-22","open":104.22,"high":104.72,"low":103.2,"close":104.04,"volume":141122},{"date":"2025-12-23","open":103.94,"high":105.44,"low":103.5,"close":104.98,"volume":677928},{"date":"2025-12-29","open":104.98,"high":106.62,"low":104.18,"close":106.06,"volume":518372},{"date":"2025-12-30","open":105.68,"high":106.18,"low":105.12,"close":105.94,"volume":225828},{"date":"2026-01-02","open":106.12,"high":106.32,"low":102.3,"close":102.3,"volume":516734},{"date":"2026-01-05","open":103.66,"high":105.0,"low":103.3,"close":103.36,"volume":309203},{"date":"2026-01-07","open":104.3,"high":104.96,"low":102.62,"close":104.08,"volume":456248},{"date":"2026-01-08","open":104.14,"high":105.58,"low":103.86,"close":103.98,"volume":330357},{"date":"2026-01-09","open":104.02,"high":105.06,"low":103.78,"close":104.56,"volume":176658},{"date":"2026-01-12","open":104.02,"high":104.56,"low":103.2,"close":103.7,"volume":414331},{"date":"2026-01-13","open":103.14,"high":104.96,"low":103.06,"close":104.68,"volume":224334},{"date":"2026-01-14","open":104.0,"high":104.72,"low":103.1,"close":104.7,"volume":242664},{"date":"2026-01-15","open":105.0,"high":107.3,"low":104.1,"close":107.04,"volume":360087},{"date":"2026-01-16","open":107.04,"high":107.04,"low":104.2,"close":104.44,"volume":453739},{"date":"2026-01-19","open":103.6,"high":103.6,"low":99.66,"close":101.02,"volume":562481},{"date":"2026-01-20","open":101.02,"high":101.22,"low":99.85,"close":100.72,"volume":749313},{"date":"2026-01-21","open":100.7,"high":100.78,"low":99.39,"close":100.32,"volume":358953},{"date":"2026-01-22","open":101.24,"high":102.58,"low":100.68,"close":100.82,"volume":174361},{"date":"2026-01-23","open":100.74,"high":101.04,"low":100.12,"close":100.46,"volume":244683},{"date":"2026-01-26","open":100.1,"high":101.32,"low":99.87,"close":100.5,"volume":668417},{"date":"2026-01-27","open":100.5,"high":105.12,"low":100.5,"close":104.1,"volume":426927},{"date":"2026-01-28","open":104.1,"high":105.3,"low":103.8,"close":104.8,"volume":219114},{"date":"2026-01-29","open":104.8,"high":107.0,"low":104.8,"close":106.2,"volume":384783},{"date":"2026-01-30","open":106.4,"high":107.74,"low":106.0,"close":106.8,"volume":422146},{"date":"2026-02-02","open":106.66,"high":108.04,"low":105.26,"close":107.62,"volume":293664},{"date":"2026-02-03","open":107.62,"high":108.22,"low":106.72,"close":107.24,"volume":369513},{"date":"2026-02-04","open":106.18,"high":108.32,"low":106.18,"close":107.96,"volume":404496},{"date":"2026-02-05","open":107.78,"high":108.4,"low":106.5,"close":108.12,"volume":586603},{"date":"2026-02-06","open":107.6,"high":108.48,"low":106.44,"close":108.2,"volume":248003},{"date":"2026-02-09","open":108.2,"high":108.78,"low":107.58,"close":108.5,"volume":243269},{"date":"2026-02-10","open":108.0,"high":112.76,"low":108.0,"close":112.12,"volume":217615},{"date":"2026-02-11","open":112.12,"high":112.12,"low":107.92,"close":108.0,"volume":574452},{"date":"2026-02-12","open":106.2,"high":110.22,"low":106.2,"close":108.6,"volume":480681},{"date":"2026-02-13","open":109.12,"high":109.76,"low":107.96,"close":109.18,"volume":244702},{"date":"2026-02-16","open":110.38,"high":110.96,"low":108.48,"close":109.18,"volume":178853},{"date":"2026-02-17","open":109.12,"high":111.46,"low":107.46,"close":108.58,"volume":364860},{"date":"2026-02-18","open":108.0,"high":110.82,"low":107.32,"close":108.74,"volume":441824},{"date":"2026-02-19","open":116.0,"high":118.0,"low":106.0,"close":110.38,"volume":1883449},{"date":"2026-02-20","open":113.0,"high":116.74,"low":112.3,"close":115.0,"volume":1149398},{"date":"2026-02-23","open":115.0,"high":115.0,"low":110.9,"close":111.58,"volume":705399},{"date":"2026-02-24","open":110.6,"high":113.0,"low":109.72,"close":112.18,"volume":321164},{"date":"2026-02-25","open":112.4,"high":112.5,"low":110.5,"close":110.72,"volume":551216},{"date":"2026-02-26","open":110.64,"high":111.78,"low":109.72,"close":111.4,"volume":198500},{"date":"2026-02-27","open":111.4,"high":111.98,"low":109.12,"close":110.54,"volume":456713},{"date":"2026-03-02","open":107.18,"high":108.48,"low":106.02,"close":106.3,"volume":261858},{"date":"2026-03-03","open":104.9,"high":104.9,"low":100.7,"close":101.34,"volume":524471},{"date":"2026-03-04","open":101.1,"high":103.08,"low":100.5,"close":102.12,"volume":225430},{"date":"2026-03-05","open":102.46,"high":103.38,"low":101.5,"close":102.48,"volume":198452},{"date":"2026-03-06","open":102.7,"high":104.5,"low":102.14,"close":102.26,"volume":156313},{"date":"2026-03-09","open":100.0,"high":101.54,"low":99.02,"close":99.83,"volume":278129},{"date":"2026-03-10","open":102.0,"high":103.86,"low":101.56,"close":102.4,"volume":165458},{"date":"2026-03-11","open":102.28,"high":102.8,"low":101.02,"close":101.84,"volume":124990},{"date":"2026-03-12","open":101.9,"high":102.5,"low":100.46,"close":101.88,"volume":181981},{"date":"2026-03-13","open":101.88,"high":103.52,"low":101.0,"close":102.78,"volume":207639},{"date":"2026-03-16","open":102.64,"high":103.22,"low":101.04,"close":102.5,"volume":151072},{"date":"2026-03-17","open":102.34,"high":104.66,"low":101.28,"close":102.58,"volume":162256},{"date":"2026-03-18","open":102.72,"high":103.32,"low":100.7,"close":101.3,"volume":179607},{"date":"2026-03-19","open":100.06,"high":100.12,"low":96.83,"close":97.03,"volume":504628},{"date":"2026-03-20","open":97.78,"high":98.1,"low":95.1,"close":95.93,"volume":363143},{"date":"2026-03-23","open":93.01,"high":98.15,"low":91.28,"close":96.07,"volume":397152},{"date":"2026-03-24","open":96.31,"high":98.03,"low":95.74,"close":97.52,"volume":340600},{"date":"2026-03-25","open":98.3,"high":99.22,"low":97.88,"close":98.65,"volume":213662},{"date":"2026-03-26","open":98.44,"high":102.84,"low":98.43,"close":102.34,"volume":435746},{"date":"2026-03-27","open":102.4,"high":103.2,"low":101.22,"close":103.04,"volume":304052},{"date":"2026-03-30","open":103.02,"high":104.5,"low":100.18,"close":104.34,"volume":313307},{"date":"2026-03-31","open":104.58,"high":106.68,"low":104.5,"close":106.34,"volume":312433},{"date":"2026-04-01","open":108.88,"high":109.78,"low":107.0,"close":107.5,"volume":189355},{"date":"2026-04-02","open":106.5,"high":107.9,"low":105.98,"close":106.24,"volume":116517},{"date":"2026-04-07","open":108.0,"high":109.2,"low":105.0,"close":105.3,"volume":453305},{"date":"2026-04-08","open":110.0,"high":111.0,"low":108.6,"close":110.4,"volume":533836},{"date":"2026-04-09","open":110.3,"high":112.1,"low":109.5,"close":111.5,"volume":529922},{"date":"2026-04-10","open":111.8,"high":113.2,"low":111.7,"close":111.7,"volume":321536},{"date":"2026-04-13","open":111.6,"high":112.9,"low":110.9,"close":112.4,"volume":235924},{"date":"2026-04-14","open":113.0,"high":115.3,"low":112.3,"close":114.9,"volume":217328},{"date":"2026-04-15","open":114.7,"high":117.1,"low":114.6,"close":117.1,"volume":138656},{"date":"2026-04-16","open":117.2,"high":120.0,"low":117.2,"close":120.0,"volume":200439},{"date":"2026-04-17","open":120.0,"high":122.4,"low":120.0,"close":121.7,"volume":259160},{"date":"2026-04-20","open":124.4,"high":125.0,"low":121.8,"close":123.6,"volume":438849},{"date":"2026-04-21","open":124.0,"high":125.7,"low":123.4,"close":124.0,"volume":314886},{"date":"2026-04-22","open":124.0,"high":124.5,"low":123.0,"close":123.1,"volume":165117},{"date":"2026-04-23","open":123.1,"high":124.1,"low":121.4,"close":124.1,"volume":212181},{"date":"2026-04-24","open":123.3,"high":124.4,"low":122.7,"close":123.3,"volume":171773},{"date":"2026-04-27","open":123.3,"high":124.3,"low":122.7,"close":122.7,"volume":191739},{"date":"2026-04-28","open":122.3,"high":122.5,"low":121.2,"close":122.1,"volume":357880},{"date":"2026-04-29","open":122.1,"high":122.9,"low":121.7,"close":122.1,"volume":105840},{"date":"2026-04-30","open":121.0,"high":123.9,"low":120.5,"close":123.9,"volume":106522}]